README
setup.py
mass/__init__.py
mass/config.py
mass/monitor.py
mass/parse.py
mass/script.py
mass.egg-info/PKG-INFO
mass.egg-info/SOURCES.txt
mass.egg-info/dependency_links.txt
mass.egg-info/entry_points.txt
mass.egg-info/not-zip-safe
mass.egg-info/requires.txt
mass.egg-info/top_level.txt