Metadata-Version: 1.0
Name: mass
Version: 0.1.3
Summary: Merge and Simplify Scripts: an automated tool for managing, combining and minifying javascript assets for web projects.
Home-page: https://github.com/coded-by-hand/mass
Author: jack boberg alex padgett
Author-email: info@codedbyhand.com
License: BSD License
Platform: Mac OSX
